plone.app.registry-2.0.7-py3.13-nspkg.pth
plone/app/registry/README.txt
plone/app/registry/__init__.py
plone/app/registry/configure.zcml
plone/app/registry/registry.py
plone/app/registry/testing.py
plone/app/registry/browser/__init__.py
plone/app/registry/browser/configure.zcml
plone/app/registry/browser/controlpanel.py
plone/app/registry/browser/delete.py
plone/app/registry/browser/edit.py
plone/app/registry/browser/exportxml.py
plone/app/registry/browser/records.py
plone/app/registry/browser/resources/icon.png
plone/app/registry/browser/resources/style.css
plone/app/registry/browser/templates/controlpanel_layout.pt
plone/app/registry/browser/templates/delete_layout.pt
plone/app/registry/browser/templates/edit_layout.pt
plone/app/registry/browser/templates/exportxml.pt
plone/app/registry/browser/templates/records.pt
plone/app/registry/exportimport/__init__.py
plone/app/registry/exportimport/configure.zcml
plone/app/registry/exportimport/fields.py
plone/app/registry/exportimport/handler.py
plone/app/registry/exportimport/handlers.zcml
plone/app/registry/profiles/default/componentregistry.xml
plone/app/registry/profiles/default/controlpanel.xml
plone/app/registry/profiles/default/metadata.xml
plone/app/registry/profiles/default/toolset.xml
plone/app/registry/tests/__init__.py
plone/app/registry/tests/data.py
plone/app/registry/tests/test_controlpanel.py
plone/app/registry/tests/test_exportimport.py
plone/app/registry/tests/test_setup.py
plone_app_registry-2.0.7.dist-info/METADATA
plone_app_registry-2.0.7.dist-info/WHEEL
plone_app_registry-2.0.7.dist-info/namespace_packages.txt
plone_app_registry-2.0.7.dist-info/top_level.txt
plone_app_registry-2.0.7.dist-info/RECORD
