Metadata-Version: 2.4
Name: plone.app.registry
Version: 2.0.7
Summary: Zope 2 and Plone  integration for plone.registry
Home-page: https://pypi.org/project/plone.app.registry
Author: Martin Aspeli
Author-email: optilude@gmail.com
License: GPL
Keywords: plone registry settings configuration
Classifier: Development Status :: 5 - Production/Stable
Classifier: Environment :: Web Environment
Classifier: Framework :: Plone
Classifier: Framework :: Plone :: 6.0
Classifier: Framework :: Plone :: Core
Classifier: Framework :: Zope :: 5
Classifier: License :: OSI Approved :: GNU General Public License v2 (GPLv2)
Classifier: Operating System :: OS Independent
Classifier: Programming Language :: Python
Classifier: Programming Language :: Python :: 3.8
Classifier: Programming Language :: Python :: 3.9
Classifier: Programming Language :: Python :: 3.10
Classifier: Programming Language :: Python :: 3.11
Requires-Python: >=3.8
Requires-Dist: lxml
Requires-Dist: plone.app.z3cform
Requires-Dist: plone.autoform>=1.0
Requires-Dist: plone.base
Requires-Dist: plone.registry>=1.0
Requires-Dist: plone.supermodel>=1.1
Requires-Dist: Products.statusmessages
Requires-Dist: setuptools
Requires-Dist: Products.GenericSetup
Requires-Dist: plone.z3cform
Requires-Dist: z3c.form
Requires-Dist: Zope
Provides-Extra: test
Requires-Dist: plone.app.testing; extra == "test"
Requires-Dist: plone.testing; extra == "test"
Dynamic: author
Dynamic: author-email
Dynamic: classifier
Dynamic: description
Dynamic: description-content-type
Dynamic: home-page
Dynamic: keywords
Dynamic: license
Dynamic: provides-extra
Dynamic: requires-dist
Dynamic: requires-python
Dynamic: summary
